{
    "model": {
        "columns": {
            "firstName": {
                "type": "varchar",
                "params": {
                    "name": "firstName"
                },
                "formType": "textInput",
                "header": true
            },
            "gender": {
                "type": "int",
                "params": {
                    "name": "gender"
                },
                "formType": "selectInput",
                "header": false,
                "selections": [
                    {
                        "name": "Male",
                        "id": 1
                    },
                    {
                        "name": "Female",
                        "id": 2
                    }
                ]
            },
            "body": {
                "type": "json",
                "params": {
                    "name": "body",
                    "nullable": true
                },
                "formType": "editor",
                "header": false,
                "multiLng": true
            }
        }
    },
    "module": {
        "type": "list"
    }
}