{
    "model": {
        "columns": {
            "department": {
                "type": "int",
                "params": {
                    "name": "department"
                }
            },
            "subject": {
                "type": "varchar",
                "params": {
                    "name": "subject"
                }
            },
            "message": {
                "type": "varchar",
                "params": {
                    "name": "message",
                    "nullable": true
                }
            },
            "image": {
                "type": "json",
                "params": {
                    "name": "image",
                    "nullable": true
                }
            },
            "userId": {
                "type": "int",
                "params": {
                    "name": "userId"
                }
            },
            "lastUpdate": {
                "type": "timestamp",
                "params": {
                    "name": "lastUpdate",
                    "nullable": true
                }
            },
            "active": {
                "type": "boolean",
                "params": {
                    "name": "active",
                    "default": true
                }
            },
            "read": {
                "type": "boolean",
                "params": {
                    "name": "read",
                    "default": false
                }
            }
        }
    }
}